phylum/__init__.py
phylum/ci/__init__.py
phylum/ci/__main__.py
phylum/ci/ci_azure.py
phylum/ci/ci_base.py
phylum/ci/ci_bitbucket.py
phylum/ci/ci_github.py
phylum/ci/ci_gitlab.py
phylum/ci/ci_jenkins.py
phylum/ci/ci_none.py
phylum/ci/ci_precommit.py
phylum/ci/cli.py
phylum/ci/common.py
phylum/ci/depfile.py
phylum/ci/git.py
phylum/console.py
phylum/constants.py
phylum/exceptions.py
phylum/exts/__init__.py
phylum/exts/ci/PhylumExt.toml
phylum/exts/ci/__init__.py
phylum/exts/ci/main.ts
phylum/github.py
phylum/init/__init__.py
phylum/init/__main__.py
phylum/init/cli.py
phylum/init/sig.py
phylum/logger.py
phylum-0.59.0.dist-info/LICENSE
phylum-0.59.0.dist-info/METADATA
phylum-0.59.0.dist-info/WHEEL
phylum-0.59.0.dist-info/entry_points.txt
phylum-0.59.0.dist-info/RECORD
