Metadata-Version: 2.3
Name: phylum
Version: 0.59.0
Summary: Utilities for integrating Phylum into CI pipelines
License: GPL-3.0-or-later
Keywords: dependency,security,CI,integration
Author: Veracode Inc.
Author-email: dl-phylum-engineering@veracode.com
Requires-Python: >=3.10,<3.14
Classifier: Development Status :: 4 - Beta
Classifier: Intended Audience :: Developers
Classifier: Natural Language :: English
Classifier: Environment :: Console
Classifier: Topic :: Security
Classifier: Topic :: Software Development
Classifier: Topic :: Software Development :: Quality Assurance
Classifier: Programming Language :: Python :: 3
Classifier: Programming Language :: Python :: 3.10
Classifier: Programming Language :: Python :: 3.11
Classifier: Programming Language :: Python :: 3.12
Classifier: Programming Language :: Python :: 3.13
Requires-Dist: cryptography
Requires-Dist: packaging
Requires-Dist: pathspec
Requires-Dist: requests
Requires-Dist: rich
Requires-Dist: ruamel.yaml
Project-URL: CI, https://github.com/phylum-dev/phylum-ci/actions
Project-URL: Documentation, https://docs.phylum.io/
Project-URL: Homepage, https://veracode.com/
Project-URL: changelog, https://github.com/phylum-dev/phylum-ci/blob/main/CHANGELOG.md
Project-URL: issues, https://github.com/phylum-dev/phylum-ci/issues
Project-URL: releasenotes, https://github.com/phylum-dev/phylum-ci/releases
Project-URL: source, https://github.com/phylum-dev/phylum-ci
